README.md
setup.py
pyndf/__init__.py
pyndf/wt_compressor.py
pyndf.egg-info/PKG-INFO
pyndf.egg-info/SOURCES.txt
pyndf.egg-info/dependency_links.txt
pyndf.egg-info/not-zip-safe
pyndf.egg-info/requires.txt
pyndf.egg-info/top_level.txt